tinxy/__init__.py
tinxy/tinxy.py
tinxy/tinxycloud.py
tinxy-0.2.6.dist-info/LICENSE
tinxy-0.2.6.dist-info/METADATA
tinxy-0.2.6.dist-info/WHEEL
tinxy-0.2.6.dist-info/top_level.txt
tinxy-0.2.6.dist-info/RECORD
